{
    "url": "https://www.georgebrown.ca/programs/construction-craft-worker-foundations-program-a106?year=2023",
    "program description": "Program Description Leadership ClaimsThis program was developed in collaboration with the Centre for Addiction and Mental Health (CAMH) and is unique in Canada.\u00a0Program OverviewGeorge Brown College\u2019s Construction Craft Worker (A106) is a free, 18-week supported education program for individuals who identify mental health and/or addictions challenges as a barrier to education and employment. In a small group, hands-on setting, with experiential work opportunities and job-coaching support, students will develop the skills they need for entry-level work in Toronto's construction industry.\u00a0This program was developed in collaboration with the Centre for Addiction and Mental Health (CAMH) and is unique in Canada.Full DescriptionGeorge Brown College\u2019s Construction Craft Worker (A106) program is one of two innovative Augmented Education employment-focused programs developed in partnership with the Centre for Addiction and Mental Health (CAMH).Designed to support those with a history of mental health and/or addiction challenges, this free, 18-week program addresses common employment barriers that exist and provides training to support employment in Toronto\u2019s construction industry.Construction Craft Worker Program Overview:unique in Canada18 weeks longstarts in Aprilfull-time deliveryincludes classroom and construction lab instructionclass and construction lab time approximately 30 to 35 hours per week160 hours of work placement and workshopsgraduate with an Ontario College Certificatetutoring and support available from program coachesCareer & Postgraduate Study OpportunitiesCareer OptionsConstruction Craft Worker (A106) graduates will be qualified for entry-level construction industry jobs such as:construction labourercarpentry helpermasonry helpercement-finishing helperdemolition workerGraduates will also be qualified to work in many other areas in the building trades, including the potential to work in the retail area of the construction sector. ",
    "admission requirements": "Admission RequirementsApplicants are selected on the basis of:Ontario Secondary School Diploma or equivalentmental health and/or addictions historymature student status (19 years of age or older)Intake process involves all of the following:application completionacademic assessmentskills assessmentinterviewCourse ExemptionsDue to the nature of this employment-focused program, it is only offered in block format and, as such, cannot accommodate course exemptions. Please visit our\u00a0transfer guide for more information.How to ApplyDownload the application package or call the Augmented Education office at 416-415-5000, ext. 6790 or email a request to auged@georgebrown.ca.Pour des services en fran\u00e7ais, veuillez communiquer avec nous au 416-415-5000, poste 3111 ou par courriel \u00e0 frenchserviceinfo@georgebrown.ca. ",
    "courses": "CoursesRequired CoursesCodeCourse nameBLDG 1058Plans, Specifications and CalculationsBLDG 1059Construction Site Safety, Tools and EquipmentBLDG 1060Concrete Work, Scaffolding and HoistingBLDG 1061Construction Site WorksBLDG 1062Industry PracticumCOUN 1033Field IntegrationFAID 1003Standard First AidMATH 1100Foundation Math for Building TechnologiesMATH 1109Mathematics for Building TechnologiesWELD 1005Metal CuttingDetailed course outlines ",
    "program outcomes": "Program Learning OutcomesThe graduate has reliably demonstrated the ability to:Select, use and operate safely the tools and equipment used by construction craft workers and carpenters, masons, bricklayers and other construction-related trades.Select and apply appropriate material types for use in new residential/commercial construction and renovation.Interpret and apply relevant information in the Ontario Building Code and Occupational Health and Safety Act regulations for Construction Projects (CSAO) as they relate to construction craft worker duties and the construction industry in general.Identify unsafe conditions and take appropriate action on a job site.Interpret and visualize a finished project from an orthographical projected drawing.Apply construction processes to residential/commercial construction and common types of renovations.Solve construction-related problems using appropriate techniques in a variety of construction situations.Select, use and operate appropriate welding equipment (and gas) in order to exhibit proper metal-cutting techniques and procedures.Apply basic emergency scene management and administer basic first aid needs on job work site. ",
    "tuition and fees": "Tuition & FeesDomestic TuitionThis program is free for participants.Financial AssistanceThis program is not eligible for OSAP funding.Disclaimer: The information contained in this website is subject to change without notice. It should not be viewed as a representation, offer or warranty. Students are responsible for verifying George Brown College fee requirements. ",
    "programs details": {
        "Program Name: ": "Construction Craft Worker Foundations",
        "Code: ": " A106 ",
        "Credential: ": "Ontario College Certificate",
        "Method of Study: ": "Full-time",
        "Duration: ": "18 weeks",
        "Starting Months: ": "April",
        "Domestic Tuition: ": "This program is free for participants."
    }
}