{
    "url": "https://www.georgebrown.ca/programs/culinary-skills-program-preparatory-training-a110?year=2023",
    "program description": "Program Description Leadership ClaimsThis program was developed in collaboration with the Centre for Addiction and Mental Health (CAMH) and is unique in Canada.Program OverviewGeorge Brown College\u2019s Culinary Skills (A110) is a free, supported education program for individuals who identify mental health and/or addictions challenges as a barrier to education and employment. In a small-group, hands-on setting, with experiential work opportunities and job coaching support, the program prepares students for entry-level work in Toronto's food service industry.This program, developed in collaboration with the Centre for Addiction and Mental Health (CAMH), is designed for students who see work as part of their recovery process and is unique in Canada.\u00a0Full DescriptionThe Culinary Skills (A110) program at George Brown College is one of two innovative Augmented Education employment-focused programs designed to support those with a history of mental health and/or addiction challenges by addressing common employment barriers that exist.Developed in collaboration with the Centre for Addiction and Mental Health (CAMH), this free program provides training to support employment in the food service industry. It is offered to students who see work as part of their recovery process and helps those recovering from mental health and/or addictions challenges to take the first step toward a job in Toronto\u2019s food service industry.Culinary Skills Program Overview:unique in Canadafree, two-semester, full-time programstarts in Septemberincludes classroom and kitchen lab instructionclass and kitchen lab time approximately 30 to 35 hours per week150 hours of work placement and workshopstutoring and support are available from program coachesstudents graduate with an Ontario College CertificateCareer & Postgraduate Study OpportunitiesCareer OptionsGraduates of George Brown's Culinary Skills program will be qualified for entry-level food preparation jobs in commercial food service, cafeterias, fast food outlets, restaurants and catering operations. ",
    "admission requirements": "Admission RequirementsApplicants are selected on the basis of:Ontario Secondary School Diploma or equivalentmental health and/or addictions historymature student status (19 years of age or older)Intake process involves all of the following:application completionacademic assessmentskills assessmentinterviewCourse ExemptionsDue to the nature of this employment focused program, it is only offered in block format and as such cannot accommodate course exemptions. Please visit our\u00a0transfer guide for more information.How to ApplyDownload the application package or call the Augmented Education office at 416-415-5000, ext. 6790 or email a request to auged@georgebrown.ca.Pour des services en fran\u00e7ais, veuillez communiquer avec nous au 416-415-5000, poste 3111 ou par courriel \u00e0 frenchserviceinfo@georgebrown.ca. ",
    "courses": "CoursesRequired CoursesSEMESTER 1CodeCourse NameHOSF 1233Baking Pastry and Theory \u2013 BasicHOSF 1002Baking and Pastry for CooksHOSF 1202Culinary FoundationsHOSF 1029Theory of Food IHOSF 1145SanitationHOSF 1237Field Integration/Workshops IMATH 1000Mathematics Foundations for HospitalityHOSF 1255Nutrition Fundamentals from a Culinary PerspectiveSEMESTER 2CodeCourse NameHOSF 1185Fundamentals of ButcheryHOSF 1203Culinary EssentialsHOSF 1241Field Integration/Workshops IIHOSF 1242Baking Techniques IIHOST 1005Food Beverage and Labour Cost ControlHOSF 1244Industry PracticumMATH 1102Math for HospitalityHOSF 1146Emergency First Aid/Heartsaver CPRHOSF 1184Caf\u00e9 ProductionDetailed course outlines ",
    "program outcomes": "Program Learning OutcomesThe graduate has reliably demonstrated the ability to:Provide fundamental culinary preparation and presentation for a variety of food service environments using a range of classical and contemporary techniques.Apply basic food and bake science to food preparation to create a desired end product.Contribute to and monitor adherence of others to the provision of a well-maintained kitchen environment and to the service of food and beverage products that are free from harmful bacteria or other contaminants, adhering to health, safety, sanitation and food-handling regulations.Ensure the safe operation of the kitchen and all aspects of food preparation to promote healthy work spaces and the responsible, efficient use of resources.Support the development of menu options that reflect knowledge of nutrition and food ingredients, promote general health and well-being, respond to a range of nutritional needs and preferences and address modifications for special diets, food allergies and intolerances, as required.Apply fundamental business principles and recognized industry costing and control practices to food service operations to promote a fiscally responsible operation.Apply basic knowledge of sustainability, ethical and local food sourcing, and food security to food preparation and kitchen management, recognizing the potential impacts on food production, consumer choice and operations within the food service industry.Use technology, including contemporary kitchen equipment, for food production and promotion.Perform effectively as a member of a food and beverage preparation and service team and contribute to the success of a food-service operation by applying self-management and interpersonal skills.Develop strategies for continuous personal and professional learning to ensure currency with and responsiveness to emerging culinary techniques, regulations, and practices in the food service industry. ",
    "tuition and fees": "Tuition & FeesDomestic TuitionThis program is free for participants.Financial AssistanceThis program is not eligible for OSAP funding.Disclaimer: The information contained in this website is subject to change without notice. It should not be viewed as a representation, offer or warranty. Students are responsible for verifying George Brown College fee requirements. ",
    "programs details": {
        "Program Name: ": "Culinary Skills",
        "Code: ": " A110 ",
        "Credential: ": "Ontario College Certificate",
        "Method of Study: ": "Full-time",
        "Duration: ": "2 semesters",
        "Starting Months: ": "September",
        "Domestic Tuition: ": "This program is free for participants."
    }
}